Metadata-Version: 2.1
Name: brewblox-ispindel
Version: 0.3.0
Summary: UNKNOWN
Home-page: https://github.com/bdelbosc/brewblox-ispindel
Author: Benoit Delbosc
Author-email: bdelbosc@free.fr
License: UNKNOWN
Keywords: brewing brewpi brewblox embedded plugin service ispindel hydrometer
Platform: UNKNOWN
Classifier: Development Status :: 3 - Alpha
Classifier: License :: OSI Approved :: GNU General Public License (GPL)
Classifier: Programming Language :: Python :: 3.8
Classifier: Intended Audience :: End Users/Desktop
Classifier: Topic :: System :: Hardware
Requires-Python: >=3.8
Provides-Extra: dev
